mcp_server_fetch/__init__.py
mcp_server_fetch/__main__.py
mcp_server_fetch/server.py
mseep_mcp_server_fetch-0.6.4.dist-info/licenses/LICENSE
mseep_mcp_server_fetch-0.6.4.dist-info/METADATA
mseep_mcp_server_fetch-0.6.4.dist-info/WHEEL
mseep_mcp_server_fetch-0.6.4.dist-info/entry_points.txt
mseep_mcp_server_fetch-0.6.4.dist-info/top_level.txt
mseep_mcp_server_fetch-0.6.4.dist-info/RECORD
