Metadata-Version: 2.4
Name: mseep-mcp-server-fetch
Version: 0.6.4
Summary: A Model Context Protocol server providing tools to fetch and convert web content for usage by LLMs
Author-email: mseep <support@skydeck.ai>
Maintainer-email: Maarten Smeets <wisp1980@gmail.com>
License: MIT
Project-URL: Homepage, https://github.com/MaartenSmeets/mcp-server-fetch
Project-URL: Bug-Tracker, https://github.com/MaartenSmeets/mcp-server-fetch/issues
Keywords: http,mcp,llm,automation
Classifier: Development Status :: 4 - Beta
Classifier: Intended Audience :: Developers
Classifier: License :: OSI Approved :: MIT License
Classifier: Programming Language :: Python :: 3
Classifier: Programming Language :: Python :: 3.12
Requires-Python: >=3.12
License-File: LICENSE
Requires-Dist: setuptools>=68.0.0
Requires-Dist: fastapi==0.100.1
Requires-Dist: uvicorn==0.34.0
Requires-Dist: pillow>=10.2.0
Requires-Dist: pytesseract>=0.3.10
Requires-Dist: requests>=2.32.3
Requires-Dist: beautifulsoup4>=4.12.3
Requires-Dist: numpy>=1.26.0
Requires-Dist: selenium>=4.18.0
Requires-Dist: undetected-chromedriver>=3.5.5
Requires-Dist: layoutparser>=0.3.4
Requires-Dist: torch==2.2.0+cpu
Requires-Dist: torchvision==0.17.0+cpu
Requires-Dist: torchaudio==2.2.0+cpu
Requires-Dist: pydantic>=2.0.0
Requires-Dist: pydantic-settings==2.8.1
Requires-Dist: markdownify>=0.13.1
Requires-Dist: mcp>=1.1.3
Requires-Dist: protego>=0.3.1
Requires-Dist: readabilipy>=0.2.0
Requires-Dist: httpx>=0.27.0
Requires-Dist: python-docx>=0.8.11
Requires-Dist: PyPDF2>=3.0.0
Requires-Dist: python-pptx>=0.6.21
Dynamic: license-file
